mlrequest/__init__.py
mlrequest/mlrequest.py
mlrequest/regions.py
mlrequest-python/__init__.py
mlrequest-python/mlrequest.py
test/__init__.py
test/test_mlrequest.py
mlrequest-1.1.3.dist-info/LICENSE
mlrequest-1.1.3.dist-info/METADATA
mlrequest-1.1.3.dist-info/WHEEL
mlrequest-1.1.3.dist-info/top_level.txt
mlrequest-1.1.3.dist-info/RECORD
