Metadata-Version: 2.1
Name: mlrequest
Version: 1.1.3
Summary: Python client for the mlrequest machine learning API.
Home-page: https://github.com/mlrequest/mlrequest-python
Author: Mathieu Rodrigue
Author-email: support@mlrequest.com
License: UNKNOWN
Platform: UNKNOWN
Classifier: Programming Language :: Python :: 3
Classifier: License :: OSI Approved :: MIT License
Classifier: Operating System :: OS Independent
Requires-Python: >=3.5
Requires-Dist: requests-futures
Requires-Dist: requests
Requires-Dist: sklearn-json
